main.py
shapemodule-0.0.1.dist-info/METADATA
shapemodule-0.0.1.dist-info/WHEEL
shapemodule-0.0.1.dist-info/top_level.txt
shapemodule-0.0.1.dist-info/RECORD
