Metadata-Version: 2.4
Name: ShapeModule
Version: 0.0.1
Summary: Shape optimization via PDE-constrained variational problems.
Requires-Python: >=3.10
